.gitignore
HISTORY.txt
MANIFEST.in
README.rst
bootstrap.py
buildout.cfg
plone.cfg
setup.cfg
setup.py
collective/__init__.py
collective.maplocbehavior.egg-info/PKG-INFO
collective.maplocbehavior.egg-info/SOURCES.txt
collective.maplocbehavior.egg-info/dependency_links.txt
collective.maplocbehavior.egg-info/entry_points.txt
collective.maplocbehavior.egg-info/namespace_packages.txt
collective.maplocbehavior.egg-info/not-zip-safe
collective.maplocbehavior.egg-info/requires.txt
collective.maplocbehavior.egg-info/top_level.txt
collective/maplocbehavior/__init__.py
collective/maplocbehavior/mappable.py
collective/maplocbehavior/tests.py
docs/INSTALL.txt
docs/LICENSE.GPL
docs/LICENSE.txt