Metadata-Version: 1.1
Name: collective.maplocbehavior
Version: 1.2
Summary: Provides map location behavior for Dexterity content types
Home-page: https://github.com/collective/collective.maplocbehavior
Author: Steve McMahon
Author-email: steve@dcn.org
License: GPL
Platform: UNKNOWN
Classifier: Framework :: Plone
Classifier: Programming Language :: Python
Classifier: Topic :: Software Development :: Libraries :: Python Modules
